{"ErrorFound": "NO", "ErrorNumber": "ERR01070", "ErrorMessage": "Card created successfully", "CardNumber": "512230******7991", "AccountNumber": "1100001000012430", "AdminNumber": "8738", "CardStatus": "ACTIVE", "SecondaryCardType": "1", "ExpirationDate": "02/28/2023 23:59:57:000", "ClosedDate": "", "CVV": null, "CurrentCardBalance": 15000.0, "FirstName": null, "LastName": null, "CardHolderIdentified": null, "ActivationRequired": null, "ActualLimit": "15000.00", "CVC2": "833", "ValidFrom": "02/06/2018", "ValidTo": "02/28/2023", "NameOnCard": "", "ManualCardStatus": "1", "PrimaryExpiryDate": null, "InstitutionID": "6969", "MerchantID": "14992", "ProgramID": "7131", "ResponseID": "3493", "CardCycleGroupIdentifier": 3498, "AccountUUID": "548550fe-8f43-4e07-aaa7-ae99bf70996c", "AdminUUID": "c8852b6b-bed0-40f7-b172-572b440b4042", "AdminUniversalUniqueID": "c8852b6b-bed0-40f7-b172-572b440b4042", "ClientId": "feeec166-c4a4-4a25-bbff-14109db6d362", "CustomerUUID": "bccdb3a2-0ece-450c-a021-5f99e30ff8b2"}