{"ErrorFound": "NO", "ErrorNumber": "ERR01070", "ErrorMessage": "Card created successfully", "CardNumber": "512230******8672", "AccountNumber": "1100001000015441", "AdminNumber": "9638", "CardStatus": "ACTIVE", "SecondaryCardType": "1", "ExpirationDate": "02/28/2023 23:59:57:000", "ClosedDate": "", "CVV": null, "CurrentCardBalance": 15000.0, "FirstName": null, "LastName": null, "CardHolderIdentified": null, "ActivationRequired": null, "ActualLimit": "15000.00", "CVC2": "826", "ValidFrom": "02/06/2018", "ValidTo": "02/28/2023", "NameOnCard": "", "ManualCardStatus": "1", "PrimaryExpiryDate": null, "InstitutionID": "6969", "MerchantID": "14992", "ProgramID": "7131", "ResponseID": "4092", "CardCycleGroupIdentifier": 4098, "AccountUUID": "9523a7b8-1aea-469f-ba32-7fe18a6ac323", "AdminUUID": "5174cb4e-58e3-465e-a958-e880a173398b", "AdminUniversalUniqueID": "5174cb4e-58e3-465e-a958-e880a173398b", "ClientId": "0e0e8738-9fec-45cd-b423-2600ba02595c", "CustomerUUID": "6a80536e-8471-4374-bf23-d47f218a5767"}