{"ErrorFound": "NO", "ErrorNumber": "ERR01070", "ErrorMessage": "Card created successfully", "CardNumber": "512230******5236", "AccountNumber": "1100001000010343", "AdminNumber": "8107", "CardStatus": "ACTIVE", "SecondaryCardType": "1", "ExpirationDate": "02/28/2023 23:59:57:000", "ClosedDate": "", "CVV": null, "CurrentCardBalance": 15000.0, "FirstName": null, "LastName": null, "CardHolderIdentified": null, "ActivationRequired": null, "ActualLimit": "15000.00", "CVC2": "154", "ValidFrom": "02/06/2018", "ValidTo": "02/28/2023", "NameOnCard": "", "ManualCardStatus": "1", "PrimaryExpiryDate": null, "InstitutionID": "6969", "MerchantID": "14992", "ProgramID": "7131", "ResponseID": "3072", "CardCycleGroupIdentifier": 3077, "AccountUUID": "4ea05aa7-c67c-45f2-86ef-9483612e3ef2", "AdminUUID": "37f80bbc-b065-4463-a370-01eafc46dfe1", "AdminUniversalUniqueID": "37f80bbc-b065-4463-a370-01eafc46dfe1", "ClientId": "dfd6ac40-1ca4-472c-8f1e-b92900d23526", "CustomerUUID": "6e2f7fc9-e17b-4bb7-8bbc-68a8662d6580"}