{"ErrorFound": "NO", "ErrorNumber": "ERR01070", "ErrorMessage": "Card created successfully", "CardNumber": "512230******3667", "AccountNumber": "1100001000015342", "AdminNumber": "9610", "CardStatus": "ACTIVE", "SecondaryCardType": "1", "ExpirationDate": "02/28/2023 23:59:57:000", "ClosedDate": "", "CVV": null, "CurrentCardBalance": 15000.0, "FirstName": null, "LastName": null, "CardHolderIdentified": null, "ActivationRequired": null, "ActualLimit": "15000.00", "CVC2": "727", "ValidFrom": "02/06/2018", "ValidTo": "02/28/2023", "NameOnCard": "", "ManualCardStatus": "1", "PrimaryExpiryDate": null, "InstitutionID": "6969", "MerchantID": "14992", "ProgramID": "7131", "ResponseID": "4075", "CardCycleGroupIdentifier": 4076, "AccountUUID": "680749e4-bcf7-4547-a016-ef4a70d4f762", "AdminUUID": "6f52a0f5-231b-4f30-9071-a16a77ef1c9f", "AdminUniversalUniqueID": "6f52a0f5-231b-4f30-9071-a16a77ef1c9f", "ClientId": "3330b346-58b1-40fc-96bb-cf61e8eff9a4", "CustomerUUID": "e57c5098-a9f6-4be7-b206-e445e5768fa0"}