{"ErrorFound": "NO", "ErrorNumber": "ERR01070", "ErrorMessage": "Card created successfully", "CardNumber": "512230******5984", "AccountNumber": "1100001000016639", "AdminNumber": "9991", "CardStatus": "ACTIVE", "SecondaryCardType": "1", "ExpirationDate": "02/28/2023 23:59:57:000", "ClosedDate": "", "CVV": null, "CurrentCardBalance": 15000.0, "FirstName": null, "LastName": null, "CardHolderIdentified": null, "ActivationRequired": null, "ActualLimit": "15000.00", "CVC2": "243", "ValidFrom": "02/06/2018", "ValidTo": "02/28/2023", "NameOnCard": "", "ManualCardStatus": "1", "PrimaryExpiryDate": null, "InstitutionID": "6969", "MerchantID": "14992", "ProgramID": "7131", "ResponseID": "4329", "CardCycleGroupIdentifier": 4333, "AccountUUID": "010008ac-1700-409c-b586-cebcbd57f34b", "AdminUUID": "bce5bbee-f929-4684-a3cc-003ce65793ca", "AdminUniversalUniqueID": "bce5bbee-f929-4684-a3cc-003ce65793ca", "ClientId": "faed3006-b1ae-45f7-9738-48d37fdf7a42", "CustomerUUID": "3c04d828-c6af-469e-942e-337a828ba5b1"}