{"ErrorFound": "NO", "ErrorNumber": "ERR01070", "ErrorMessage": "Card created successfully", "CardNumber": "512230******0868", "AccountNumber": "1100001000019823", "AdminNumber": "10952", "CardStatus": "ACTIVE", "SecondaryCardType": "1", "ExpirationDate": "02/28/2023 23:59:57:000", "ClosedDate": "", "CVV": null, "CurrentCardBalance": 15000.0, "FirstName": null, "LastName": null, "CardHolderIdentified": null, "ActivationRequired": null, "ActualLimit": "15000.00", "CVC2": "114", "ValidFrom": "02/06/2018", "ValidTo": "02/28/2023", "NameOnCard": "", "ManualCardStatus": "1", "PrimaryExpiryDate": null, "InstitutionID": "6969", "MerchantID": "14992", "ProgramID": "7131", "ResponseID": "4968", "CardCycleGroupIdentifier": 4973, "AccountUUID": "f5589d18-cb93-4530-9cfc-071facf7a5dc", "AdminUUID": "55a5b326-707b-472b-b5b3-f61fd034d294", "AdminUniversalUniqueID": "55a5b326-707b-472b-b5b3-f61fd034d294", "ClientId": "2266b2d8-9bf6-4c3b-9bf6-471d7f2b2da0", "CustomerUUID": "790f29c1-b482-4df2-a74b-312dfc2e429a"}