{"ErrorFound": "NO", "ErrorNumber": "ERR01070", "ErrorMessage": "Card created successfully", "CardNumber": "512230******8517", "AccountNumber": "1100001000000930", "AdminNumber": "5277", "CardStatus": "ACTIVE", "SecondaryCardType": "1", "ExpirationDate": "02/28/2023 23:59:57:000", "ClosedDate": "", "CVV": null, "CurrentCardBalance": 15000.0, "FirstName": null, "LastName": null, "CardHolderIdentified": null, "ActivationRequired": null, "ActualLimit": "15000.00", "CVC2": "026", "ValidFrom": "02/06/2018", "ValidTo": "02/28/2023", "NameOnCard": "", "ManualCardStatus": "1", "PrimaryExpiryDate": null, "InstitutionID": "6969", "MerchantID": "14992", "ProgramID": "7131", "ResponseID": "1185", "CardCycleGroupIdentifier": 1190, "AccountUUID": "237e9001-70cb-48f1-a455-62ad4a746035", "AdminUUID": "f8b875a0-ea3e-498b-9de6-ff968101066f", "AdminUniversalUniqueID": "f8b875a0-ea3e-498b-9de6-ff968101066f", "ClientId": "039e387c-c255-49a0-a43c-e804868ca16c", "CustomerUUID": "1a837e63-fc29-469e-8e04-75cca8e2bbba"}