{"ErrorFound": "NO", "ErrorNumber": "ERR01070", "ErrorMessage": "Card created successfully", "CardNumber": "512230******7822", "AccountNumber": "1100001000018668", "AdminNumber": "10601", "CardStatus": "ACTIVE", "SecondaryCardType": "1", "ExpirationDate": "02/28/2023 23:59:57:000", "ClosedDate": "", "CVV": null, "CurrentCardBalance": 15000.0, "FirstName": null, "LastName": null, "CardHolderIdentified": null, "ActivationRequired": null, "ActualLimit": "15000.00", "CVC2": "446", "ValidFrom": "02/06/2018", "ValidTo": "02/28/2023", "NameOnCard": "", "ManualCardStatus": "1", "PrimaryExpiryDate": null, "InstitutionID": "6969", "MerchantID": "14992", "ProgramID": "7131", "ResponseID": "4734", "CardCycleGroupIdentifier": 4739, "AccountUUID": "e2188d2b-5d1b-4403-a8fb-d8bfb45d1372", "AdminUUID": "bd2042fc-4261-4c3b-953b-0648f5e3521b", "AdminUniversalUniqueID": "bd2042fc-4261-4c3b-953b-0648f5e3521b", "ClientId": "4a83be28-7533-4e8d-ab9b-3844a4b1e6e0", "CustomerUUID": "6430695a-6dd9-4c37-b065-f928a09feb1a"}