{"ErrorFound": "NO", "ErrorNumber": "ERR01070", "ErrorMessage": "Card created successfully", "CardNumber": "512230******5200", "AccountNumber": "1100001000005301", "AdminNumber": "6587", "CardStatus": "ACTIVE", "SecondaryCardType": "1", "ExpirationDate": "02/28/2023 23:59:57:000", "ClosedDate": "", "CVV": null, "CurrentCardBalance": 15000.0, "FirstName": null, "LastName": null, "CardHolderIdentified": null, "ActivationRequired": null, "ActualLimit": "15000.00", "CVC2": "630", "ValidFrom": "02/06/2018", "ValidTo": "02/28/2023", "NameOnCard": "", "ManualCardStatus": "1", "PrimaryExpiryDate": null, "InstitutionID": "6969", "MerchantID": "14992", "ProgramID": "7131", "ResponseID": "2059", "CardCycleGroupIdentifier": 2064, "AccountUUID": "f2bca41b-a3c6-4137-8d4d-6478f1e4cf47", "AdminUUID": "dd826964-ddc8-4898-8b12-5fa0deccbb4c", "AdminUniversalUniqueID": "dd826964-ddc8-4898-8b12-5fa0deccbb4c", "ClientId": "d0bb3794-75e9-4c97-8cd4-d0ff2b4b2dde", "CustomerUUID": "1c7fab26-ed74-4ffb-9c64-6d311ca609d2"}