{"ErrorFound": "NO", "ErrorNumber": "ERR01070", "ErrorMessage": "Card created successfully", "CardNumber": "512230******3766", "AccountNumber": "1100001000010368", "AdminNumber": "8111", "CardStatus": "ACTIVE", "SecondaryCardType": "1", "ExpirationDate": "02/28/2023 23:59:57:000", "ClosedDate": "", "CVV": null, "CurrentCardBalance": 15000.0, "FirstName": null, "LastName": null, "CardHolderIdentified": null, "ActivationRequired": null, "ActualLimit": "15000.00", "CVC2": "711", "ValidFrom": "02/06/2018", "ValidTo": "02/28/2023", "NameOnCard": "", "ManualCardStatus": "1", "PrimaryExpiryDate": null, "InstitutionID": "6969", "MerchantID": "14992", "ProgramID": "7131", "ResponseID": "3074", "CardCycleGroupIdentifier": 3079, "AccountUUID": "8ac0e2cc-74cd-49cd-9939-3e14e57c2201", "AdminUUID": "89411e5f-2baa-450e-9138-5db22c5ebe2a", "AdminUniversalUniqueID": "89411e5f-2baa-450e-9138-5db22c5ebe2a", "ClientId": "126780d7-a798-4474-981a-4d843bb52d4d", "CustomerUUID": "4c4a5983-0d26-4c7a-9942-3142691cd59b"}