{"ErrorFound": "NO", "ErrorNumber": "ERR01070", "ErrorMessage": "Card created successfully", "CardNumber": "512230******5553", "AccountNumber": "1100001000004809", "AdminNumber": "6445", "CardStatus": "ACTIVE", "SecondaryCardType": "1", "ExpirationDate": "02/28/2023 23:59:57:000", "ClosedDate": "", "CVV": null, "CurrentCardBalance": 15000.0, "FirstName": null, "LastName": null, "CardHolderIdentified": null, "ActivationRequired": null, "ActualLimit": "15000.00", "CVC2": "993", "ValidFrom": "02/06/2018", "ValidTo": "02/28/2023", "NameOnCard": "", "ManualCardStatus": "1", "PrimaryExpiryDate": null, "InstitutionID": "6969", "MerchantID": "14992", "ProgramID": "7131", "ResponseID": "1964", "CardCycleGroupIdentifier": 1969, "AccountUUID": "874742ea-f1fa-48d0-9d49-6fb9c8a84a62", "AdminUUID": "1fdae0f4-a201-4d9d-9bec-ab8ce5ae12cc", "AdminUniversalUniqueID": "1fdae0f4-a201-4d9d-9bec-ab8ce5ae12cc", "ClientId": "2762926a-e5a6-46c5-ad45-04e3e61e7403", "CustomerUUID": "6b20ecff-aedf-4da1-acff-2b9a5cf63cbd"}