[
  {
    "Source": "AccountLevel",
    "acctID": "14551612",
    "AccountNumber": "1100001000006739",
    "UniversalUniqueID": "1fb62390-1ff5-4e96-a27d-5f0783c2a3bf",
    "DateAcctOpened": "2018-04-03 00:00:58",
    "LastStatementDate": "2018-04-30 23:59:57",
    "SystemStatus": "2",
    "CCINHPARENT125AID": "2",
    "CurrentBalance": "2,000.00",
    "CurrentBalanceCO": "0.00",
    "Principal": "2,000.00",
    "PrincipalCO": "0.00",
    "IntBilledNotPaid": "0.00",
    "recoveryfeesbnp": "0.00",
    "recoveryfeesbnpco": "0.00",
    "latefeesbnp": "0.00",
    "latefeesbnpco": "0.00",
    "CycleDueDTD": "1",
    "DateOfTotalDue": "2018-05-31 23:59:57",
    "SRBWithInstallmentDue": "2,000.00",
    "AmountOfTotalDue": "25.00",
    "AmtOfPayCurrDue": "25.00",
    "AmtOfPayXDLate": "0.00",
    "AmountOfPayment30DLate": "0.00",
    "AmountOfPayment60DLate": "0.00",
    "AmountOfPayment90DLate": "0.00",
    "AmountOfPayment120DLate": "0.00",
    "AmountOfPayment150DLate": "0.00",
    "AmountOfPayment180DLate": "0.00",
    "AmountOfPayment210DLate": "0.00",
    "RunningMinimumDue": "25.00",
    "RemainingMinimumDue": "25.00",
    "AmtOfCrAdjMSBCTD": "0.00",
    "LateFeePBNP": "0.00",
    "DtOfLastDelinqCTD": null,
    "DateOfOriginalPaymentDueDTD": null,
    "daysdelinquent": "0",
    "NoPayDaysDelinquent": "0",
    "AmtOfAcctHighBalLTD": "2,000.00",
    "DisputesAmtNS": "0.00",
    "BeginningBalance": "2,000.00",
    "AmountOfDebitsCTD": "0.00",
    "AmountofCreditsCTD": "0.00",
    "AmountOfDebitsRevCTD": "0.00",
    "AmountOfCreditsRevCTD": "0.00",
    "AmountOfPaymentsCTD": "0.00",
    "AmtofInterestCTD": "0.00",
    "servicefeesbnp": "0.00",
    "ServiceChargeCTD": "0.00",
    "LateChargesCTD": "0.00",
    "RecoveryFeesCTD": "0.00",
    "InstitutionID": "6969",
    "ccinhparent127AID": "10368",
    "UserChargeOffStatus": "0",
    "SystemChargeOffStatus": "0",
    "AutoInitialChargeOffStartDate": null,
    "ManualInitialChargeOffStartDate": null,
    "ChargeOffDateParam": null,
    "ChargeOffDate": null,
    "AccountGraceStatus": "T",
    "GraceDaysStatus": "0",
    "OriginalSettlementAmount": "0.00",
    "BilledSettlementAmount": "0.00",
    "MonthlySettlementAmount": "0.00",
    "SettlementGracePeriodEndDate": null,
    "SettlementWriteOffDate": null,
    "ProgramStartDate": null,
    "ProgramEndDate": null,
    "ProgramStatus": "0",
    "CreditsDuringProgram": "0.00",
    "CreditsDuringProgramCTD": "0.00",
    "PaymentDuringProgram": "0.00",
    "NearestEffectiveEndDate": null,
    "EffectiveEndDate_Acct": null,
    "Plan": {
      "Plan_1": {
        "Source": "PlanLevel",
        "acctID": "40755718",
        "PlanCount": "1",
        "parent02AID": "14551612",
        "CreditPlanType": "0",
        "PlanSegCreateDate": "2018-04-03 14:34:01",
        "PlanUUID": null,
        "OriginalPurchaseAmount": "0.00",
        "EqualPaymentAmt": "0.00",
        "CurrentBalance": "2,000.00",
        "CurrentBalanceCO": "0.00",
        "decurrentbalance_trantime_ps": "2,000.00",
        "Principal": "2,000.00",
        "PrincipalCO": "0.00",
        "CycleDueDTD": "1",
        "AmountOfTotalDue": "25.00",
        "AmtOfPayCurrDue": "25.00",
        "AmtOfPayXDLate": "0.00",
        "AmountOfPayment30DLate": "0.00",
        "AmountOfPayment60DLate": "0.00",
        "AmountOfPayment90DLate": "0.00",
        "AmountOfPayment120DLate": "0.00",
        "AmountOfPayment150DLate": "0.00",
        "AmountOfPayment180DLate": "0.00",
        "AmountOfPayment210DLate": "0.00",
        "SRBWithInstallmentDue": "2,000.00",
        "EstimatedDue": "0.00",
        "RolloverDue": "0.00",
        "DisputesAmtNS": "0.00",
        "AmountOfCreditsCTD": "0.00",
        "AmountOfPaymentsCTD": "0.00",
        "MergeDate": null,
        "MergeIndicator": null,
        "intbillednotpaid": "0.00",
        "AccountGraceStatus": "T",
        "GraceDaysStatus": "0",
        "recoveryfeesbnp": "0.00",
        "recoveryfeesbnpco": "0.00",
        "beginningbalance": "2,000.00",
        "AmountOfDebitsCTD": "0.00",
        "AmountOfDebitsRevCTD": "0.00",
        "AmountOfCreditsRevLTD": "0.00"
      }
    }
  }
]