{"ErrorFound": "NO", "ErrorNumber": "ERR01070", "ErrorMessage": "Card created successfully", "CardNumber": "512230******9005", "AccountNumber": "1100001000006945", "AdminNumber": "20359033", "CardStatus": "ACTIVE", "SecondaryCardType": "1", "ExpirationDate": "02/28/2023 23:59:57:000", "ClosedDate": "", "CVV": null, "CurrentCardBalance": 15000.0, "FirstName": null, "LastName": null, "CardHolderIdentified": null, "ActivationRequired": null, "ActualLimit": "15000.00", "CVC2": "657", "ValidFrom": "02/06/2018", "ValidTo": "02/28/2023", "NameOnCard": "", "ManualCardStatus": "1", "PrimaryExpiryDate": null, "InstitutionID": "6969", "MerchantID": "14992", "ProgramID": "7131", "ResponseID": "1386572915153305706", "CardCycleGroupIdentifier": 18342364, "AccountUUID": "115bd766-ef65-4b82-b7b7-ed50702d20d8", "AdminUUID": "0403835c-148c-4a07-8a62-a3420f1f3e20", "AdminUniversalUniqueID": "0403835c-148c-4a07-8a62-a3420f1f3e20", "ClientId": "d34ed5d2-111f-44e4-ace9-970484c4d59c", "CustomerUUID": "d06995b4-f4c1-4c78-9ecb-722e8a59ebf7", "RequestorID": null, "PODID": "1"}