{"ErrorFound": "NO", "ErrorNumber": "ERR01070", "ErrorMessage": "Card created successfully", "CardNumber": "512230******2080", "AccountNumber": "1100001000007331", "AdminNumber": "20359147", "CardStatus": "ACTIVE", "SecondaryCardType": "1", "ExpirationDate": "02/28/2023 23:59:57:000", "ClosedDate": "", "CVV": null, "CurrentCardBalance": 15000.0, "FirstName": null, "LastName": null, "CardHolderIdentified": null, "ActivationRequired": null, "ActualLimit": "15000.00", "CVC2": "057", "ValidFrom": "02/06/2018", "ValidTo": "02/28/2023", "NameOnCard": "", "ManualCardStatus": "1", "PrimaryExpiryDate": null, "InstitutionID": "6969", "MerchantID": "14992", "ProgramID": "7131", "ResponseID": "1386573806698824627", "CardCycleGroupIdentifier": 18342440, "AccountUUID": "27046314-a88c-4405-8145-d644d1b45ed6", "AdminUUID": "305ee295-dfb5-427e-8211-b8d212c96b2a", "AdminUniversalUniqueID": "305ee295-dfb5-427e-8211-b8d212c96b2a", "ClientId": "7609a0ba-3c2a-4b70-9636-c86e8ef6fab9", "CustomerUUID": "88627e47-a99c-427f-8ca2-c4720ef0d852", "RequestorID": null, "PODID": "1"}