{"RecordType": "55", "ProductType": "B", "FirstName": "Prasoon", "MiddleName": null, "LastName": "Parashar", "AccountNumber": "1100001000017496", "CardNumber": "5122300000034641", "AdminNumber": "10239", "CustomerID": "6749", "AccountCreationDate": "02/06/2018", "AccountCreationTime": "01:41:17", "TerminalID": "WEB", "ErrorNumber": "ERR01002", "ErrorMessage": "Account Creation Successful", "ResponseID": "4494", "ErrorFound": "NO", "CVV": "575", "ExpirationDate": "02/28/2023", "UniversalUniqueID": "d660d807-6501-4530-a3e8-3d7aa9e5f8dd", "AdminUniversalUniqueID": "1dc5dae9-fab4-4153-9144-1e040ee5130d", "EmailID": null}