{"RecordType": "55", "ProductType": "B", "FirstName": "Prasoon", "MiddleName": null, "LastName": "Parashar", "AccountNumber": "1100001000018023", "CardNumber": "5122300000036737", "AdminNumber": "10402", "CustomerID": "6802", "AccountCreationDate": "02/06/2018", "AccountCreationTime": "01:42:28", "TerminalID": "WEB", "ErrorNumber": "ERR01002", "ErrorMessage": "Account Creation Successful", "ResponseID": "4602", "ErrorFound": "NO", "CVV": "986", "ExpirationDate": "02/28/2023", "UniversalUniqueID": "aafbe9ad-b77f-4443-8eca-12424259247e", "AdminUniversalUniqueID": "69533a98-aa84-49a7-bae8-6a9744a8ad73", "EmailID": null}