{"RecordType": "55", "ProductType": "B", "FirstName": "Prasoon", "MiddleName": null, "LastName": "Parashar", "AccountNumber": "1100001000010574", "CardNumber": "5122300000052627", "AdminNumber": "8165", "CustomerID": "6057", "AccountCreationDate": "02/06/2018", "AccountCreationTime": "01:25:43", "TerminalID": "WEB", "ErrorNumber": "ERR01002", "ErrorMessage": "Account Creation Successful", "ResponseID": "3111", "ErrorFound": "NO", "CVV": "552", "ExpirationDate": "02/28/2023", "UniversalUniqueID": "824b5bc4-4b49-47f3-a958-2326f23cbaee", "AdminUniversalUniqueID": "71de171d-93e6-45e7-a468-91f748613299", "EmailID": null}