{"RecordType": "55", "ProductType": "B", "FirstName": "Prasoon", "MiddleName": null, "LastName": "Parashar", "AccountNumber": "1100001000007711", "CardNumber": "5122300000036661", "AdminNumber": "7303", "CustomerID": "5771", "AccountCreationDate": "02/06/2018", "AccountCreationTime": "01:21:28", "TerminalID": "WEB", "ErrorNumber": "ERR01002", "ErrorMessage": "Account Creation Successful", "ResponseID": "2536", "ErrorFound": "NO", "CVV": null, "ExpirationDate": "02/28/2023", "UniversalUniqueID": "09535922-a2ec-4579-845e-59f108540805", "AdminUniversalUniqueID": "f5fe7772-9540-44d3-8f0b-498ccc4db921", "EmailID": null}