{"RecordType": "55", "ProductType": "B", "FirstName": "Prasoon", "MiddleName": null, "LastName": "Parashar", "AccountNumber": "1100001000009071", "CardNumber": "5122300000030102", "AdminNumber": "7711", "CustomerID": "5907", "AccountCreationDate": "02/06/2018", "AccountCreationTime": "01:23:23", "TerminalID": "WEB", "ErrorNumber": "ERR01002", "ErrorMessage": "Account Creation Successful", "ResponseID": "2809", "ErrorFound": "NO", "CVV": null, "ExpirationDate": "02/28/2023", "UniversalUniqueID": "4cb53006-84a6-468f-a5ac-28e6d63be23f", "AdminUniversalUniqueID": "7e55b74e-38fe-4abf-adfd-0e4e717a4673", "EmailID": null}