{"RecordType": "55", "ProductType": "B", "FirstName": "Prasoon", "MiddleName": null, "LastName": "Parashar", "AccountNumber": "1100001000012349", "CardNumber": "5122300000042370", "AdminNumber": "8697", "CustomerID": "6235", "AccountCreationDate": "02/06/2018", "AccountCreationTime": "01:29:53", "TerminalID": "WEB", "ErrorNumber": "ERR01002", "ErrorMessage": "Account Creation Successful", "ResponseID": "3465", "ErrorFound": "NO", "CVV": "233", "ExpirationDate": "02/28/2023", "UniversalUniqueID": "0d714dee-51b5-4109-88d8-b55419d88ff3", "AdminUniversalUniqueID": "efaf71d8-b24c-49fa-96a1-78642b82c45a", "EmailID": null}