{"RecordType": "55", "ProductType": "B", "FirstName": "Prasoon", "MiddleName": null, "LastName": "Parashar", "AccountNumber": "1100001000003306", "CardNumber": "5122300000070462", "AdminNumber": "5984", "CustomerID": "5330", "AccountCreationDate": "02/06/2018", "AccountCreationTime": "01:12:51", "TerminalID": "WEB", "ErrorNumber": "ERR01002", "ErrorMessage": "Account Creation Successful", "ResponseID": "1657", "ErrorFound": "NO", "CVV": "790", "ExpirationDate": "02/28/2023", "UniversalUniqueID": "b37a9940-1ac9-46d0-90c4-ee7193b40615", "AdminUniversalUniqueID": "7f458b06-ef41-422a-a9ad-4a02dd48a2a4", "EmailID": null}