{"RecordType": "55", "ProductType": "B", "FirstName": "Prasoon", "MiddleName": null, "LastName": "Parashar", "AccountNumber": "1100001000007190", "CardNumber": "5122300000077236", "AdminNumber": "7153", "CustomerID": "5719", "AccountCreationDate": "02/06/2018", "AccountCreationTime": "01:20:48", "TerminalID": "WEB", "ErrorNumber": "ERR01002", "ErrorMessage": "Account Creation Successful", "ResponseID": "2434", "ErrorFound": "NO", "CVV": null, "ExpirationDate": "02/28/2023", "UniversalUniqueID": "d946b097-e998-4f04-801d-517f2426521c", "AdminUniversalUniqueID": "96940e26-81c2-4384-b32d-f2e97b8cd33b", "EmailID": null}