{"RecordType": "55", "ProductType": "B", "FirstName": "Prasoon", "MiddleName": null, "LastName": "Parashar", "AccountNumber": "1100001000003009", "CardNumber": "5122300000065827", "AdminNumber": "5892", "CustomerID": "5300", "AccountCreationDate": "02/06/2018", "AccountCreationTime": "01:12:10", "TerminalID": "WEB", "ErrorNumber": "ERR01002", "ErrorMessage": "Account Creation Successful", "ResponseID": "1596", "ErrorFound": "NO", "CVV": "569", "ExpirationDate": "02/28/2023", "UniversalUniqueID": "5a6da14e-e98c-4df8-aaa0-a1d2e365cf40", "AdminUniversalUniqueID": "d05be9fd-12e1-4f4f-bcba-7f83a423f2c1", "EmailID": null}