{"RecordType": "55", "ProductType": "B", "FirstName": "Prasoon", "MiddleName": null, "LastName": "Parashar", "AccountNumber": "1100001000006598", "CardNumber": "5122300000063574", "AdminNumber": "6977", "CustomerID": "5659", "AccountCreationDate": "02/06/2018", "AccountCreationTime": "01:20:00", "TerminalID": "WEB", "ErrorNumber": "ERR01002", "ErrorMessage": "Account Creation Successful", "ResponseID": "2316", "ErrorFound": "NO", "CVV": "270", "ExpirationDate": "02/28/2023", "UniversalUniqueID": "daa287f8-65b5-4d6f-8c1e-72672c64ff81", "AdminUniversalUniqueID": "e11cd8a9-d771-4cd5-8025-c9b60bc92fc9", "EmailID": null}