{"RecordType": "55", "ProductType": "B", "FirstName": "Prasoon", "MiddleName": null, "LastName": "Parashar", "AccountNumber": "1100001000009543", "CardNumber": "5122300000003885", "AdminNumber": "7855", "CustomerID": "5954", "AccountCreationDate": "02/06/2018", "AccountCreationTime": "01:23:59", "TerminalID": "WEB", "ErrorNumber": "ERR01002", "ErrorMessage": "Account Creation Successful", "ResponseID": "2904", "ErrorFound": "NO", "CVV": null, "ExpirationDate": "02/28/2023", "UniversalUniqueID": "948751ef-a069-4c35-976b-c882837957bf", "AdminUniversalUniqueID": "741a5db9-5145-4d4c-a9cd-4ec6fd4325a5", "EmailID": null}