{"RecordType": "55", "ProductType": "B", "FirstName": "Prasoon", "MiddleName": null, "LastName": "Parashar", "AccountNumber": "1100001000010467", "CardNumber": "5122300000008090", "AdminNumber": "8138", "CustomerID": "6046", "AccountCreationDate": "02/06/2018", "AccountCreationTime": "01:25:26", "TerminalID": "WEB", "ErrorNumber": "ERR01002", "ErrorMessage": "Account Creation Successful", "ResponseID": "3092", "ErrorFound": "NO", "CVV": "653", "ExpirationDate": "02/28/2023", "UniversalUniqueID": "2ccdff83-c203-4d1c-a0e5-f983ea3c0c0d", "AdminUniversalUniqueID": "f0602780-3fa2-4f1a-9067-7e717b985616", "EmailID": null}