{"RecordType": "55", "ProductType": "B", "FirstName": "Prasoon", "MiddleName": null, "LastName": "Parashar", "AccountNumber": "1100001000011770", "CardNumber": "5122300000000857", "AdminNumber": "8531", "CustomerID": "6177", "AccountCreationDate": "02/06/2018", "AccountCreationTime": "01:28:28", "TerminalID": "WEB", "ErrorNumber": "ERR01002", "ErrorMessage": "Account Creation Successful", "ResponseID": "3354", "ErrorFound": "NO", "CVV": "156", "ExpirationDate": "02/28/2023", "UniversalUniqueID": "554f41a8-047b-4405-9c1b-e30eec291075", "AdminUniversalUniqueID": "895005c8-156f-423e-903a-a75d3c9945cd", "EmailID": null}