{"RecordType": "55", "ProductType": "B", "FirstName": "Prasoon", "MiddleName": null, "LastName": "Parashar", "AccountNumber": "1100001000005491", "CardNumber": "5122300000051884", "AdminNumber": "6643", "CustomerID": "5549", "AccountCreationDate": "02/06/2018", "AccountCreationTime": "01:17:34", "TerminalID": "WEB", "ErrorNumber": "ERR01002", "ErrorMessage": "Account Creation Successful", "ResponseID": "2096", "ErrorFound": "NO", "CVV": "244", "ExpirationDate": "02/28/2023", "UniversalUniqueID": "ac94df40-831c-4bbe-9aa4-db10f66e9e87", "AdminUniversalUniqueID": "7c188d29-c78a-48e2-9a62-5edde429f5dc", "EmailID": null}