{"RecordType": "55", "ProductType": "B", "FirstName": "Prasoon", "MiddleName": null, "LastName": "Parashar", "AccountNumber": "1100001000005251", "CardNumber": "5122300000048997", "AdminNumber": "6571", "CustomerID": "5525", "AccountCreationDate": "02/06/2018", "AccountCreationTime": "01:16:57", "TerminalID": "WEB", "ErrorNumber": "ERR01002", "ErrorMessage": "Account Creation Successful", "ResponseID": "2047", "ErrorFound": "NO", "CVV": "419", "ExpirationDate": "02/28/2023", "UniversalUniqueID": "b05e5cc4-4a31-48b8-9109-fbd8e9f91d10", "AdminUniversalUniqueID": "1be40661-fde8-4cec-9f84-67c9df38dc3b", "EmailID": null}