{"RecordType": "55", "ProductType": "B", "FirstName": "Prasoon", "MiddleName": null, "LastName": "Parashar", "AccountNumber": "1100001000019484", "CardNumber": "5122300000026803", "AdminNumber": "10838", "CustomerID": "6948", "AccountCreationDate": "02/06/2018", "AccountCreationTime": "01:45:40", "TerminalID": "WEB", "ErrorNumber": "ERR01002", "ErrorMessage": "Account Creation Successful", "ResponseID": "4893", "ErrorFound": "NO", "CVV": "295", "ExpirationDate": "02/28/2023", "UniversalUniqueID": "b5d35f7c-1ed1-411a-b7f1-e463845046ce", "AdminUniversalUniqueID": "cdf70a38-5761-49c1-a0bb-c66ef45beaf5", "EmailID": null}