{"RecordType": "55", "ProductType": "B", "FirstName": "Prasoon", "MiddleName": null, "LastName": "Parashar", "AccountNumber": "1100001000011036", "CardNumber": "5122300000056669", "AdminNumber": "8305", "CustomerID": "6103", "AccountCreationDate": "02/06/2018", "AccountCreationTime": "01:26:53", "TerminalID": "WEB", "ErrorNumber": "ERR01002", "ErrorMessage": "Account Creation Successful", "ResponseID": "3204", "ErrorFound": "NO", "CVV": "726", "ExpirationDate": "02/28/2023", "UniversalUniqueID": "cc12067c-869d-4451-befd-3a8ee9ee37ff", "AdminUniversalUniqueID": "15ba8436-832a-4075-908b-b6e4ae4ffce9", "EmailID": null}