{"RecordType": "55", "ProductType": "B", "FirstName": "Prasoon", "MiddleName": null, "LastName": "Parashar", "AccountNumber": "1100001000003728", "CardNumber": "5122300000077178", "AdminNumber": "6116", "CustomerID": "5372", "AccountCreationDate": "02/06/2018", "AccountCreationTime": "01:13:47", "TerminalID": "WEB", "ErrorNumber": "ERR01002", "ErrorMessage": "Account Creation Successful", "ResponseID": "1745", "ErrorFound": "NO", "CVV": "609", "ExpirationDate": "02/28/2023", "UniversalUniqueID": "f6565c39-c277-4b47-af00-8a905e8ee82f", "AdminUniversalUniqueID": "f1022512-758f-45b9-9810-7ce5d4557f13", "EmailID": null}