{"RecordType": "55", "ProductType": "B", "FirstName": "Prasoon", "MiddleName": null, "LastName": "Parashar", "AccountNumber": "1100001000011622", "CardNumber": "5122300000012332", "AdminNumber": "8486", "CustomerID": "6162", "AccountCreationDate": "02/06/2018", "AccountCreationTime": "01:28:09", "TerminalID": "WEB", "ErrorNumber": "ERR01002", "ErrorMessage": "Account Creation Successful", "ResponseID": "3324", "ErrorFound": "NO", "CVV": "190", "ExpirationDate": "02/28/2023", "UniversalUniqueID": "4ae43ef6-09e6-4d93-94df-0880787e17d7", "AdminUniversalUniqueID": "1d4445d0-1e66-4cb8-8d19-763e2826174b", "EmailID": null}