{"RecordType": "55", "ProductType": "B", "FirstName": "Prasoon", "MiddleName": null, "LastName": "Parashar", "AccountNumber": "1100001000010350", "CardNumber": "5122300000079489", "AdminNumber": "8095", "CustomerID": "6035", "AccountCreationDate": "02/06/2018", "AccountCreationTime": "01:25:08", "TerminalID": "WEB", "ErrorNumber": "ERR01002", "ErrorMessage": "Account Creation Successful", "ResponseID": "3065", "ErrorFound": "NO", "CVV": "828", "ExpirationDate": "02/28/2023", "UniversalUniqueID": "c272864e-2c05-4846-bc36-849e1bb9ca03", "AdminUniversalUniqueID": "e3527723-7072-4d1d-acb0-fa4a8393ddbb", "EmailID": null}