{"RecordType": "55", "ProductType": "B", "FirstName": "Prasoon", "MiddleName": null, "LastName": "Parashar", "AccountNumber": "1100001000006622", "CardNumber": "5122300000034245", "AdminNumber": "6984", "CustomerID": "5662", "AccountCreationDate": "02/06/2018", "AccountCreationTime": "01:20:06", "TerminalID": "WEB", "ErrorNumber": "ERR01002", "ErrorMessage": "Account Creation Successful", "ResponseID": "2323", "ErrorFound": "NO", "CVV": null, "ExpirationDate": "02/28/2023", "UniversalUniqueID": "31e275c9-80da-4f73-8b46-0643601bea4f", "AdminUniversalUniqueID": "e9f2cdf3-83a7-46d1-8214-176901235ae1", "EmailID": null}