{"RecordType": "55", "ProductType": "B", "FirstName": "Prasoon", "MiddleName": null, "LastName": "Parashar", "AccountNumber": "1100001000013610", "CardNumber": "5122300000017984", "AdminNumber": "9077", "CustomerID": "6361", "AccountCreationDate": "02/06/2018", "AccountCreationTime": "01:32:41", "TerminalID": "WEB", "ErrorNumber": "ERR01002", "ErrorMessage": "Account Creation Successful", "ResponseID": "3719", "ErrorFound": "NO", "CVV": "100", "ExpirationDate": "02/28/2023", "UniversalUniqueID": "10264aba-938e-4c7e-a206-25a1481886d8", "AdminUniversalUniqueID": "d2e421bb-e4ee-4825-bf26-ea02209d213e", "EmailID": null}