{"RecordType": "55", "ProductType": "B", "FirstName": "Prasoon", "MiddleName": null, "LastName": "Parashar", "AccountNumber": "1100001000008883", "CardNumber": "5122300000016069", "AdminNumber": "7656", "CustomerID": "5888", "AccountCreationDate": "02/06/2018", "AccountCreationTime": "01:23:06", "TerminalID": "WEB", "ErrorNumber": "ERR01002", "ErrorMessage": "Account Creation Successful", "ResponseID": "2771", "ErrorFound": "NO", "CVV": null, "ExpirationDate": "02/28/2023", "UniversalUniqueID": "4d9db1d0-df0b-43f1-b885-6cab6e36d99c", "AdminUniversalUniqueID": "51e45325-fced-4df3-9e4e-90780c294802", "EmailID": null}